{"section_number":"8.06","section_id":"48","structure_id":"9","catch_line":"Evaluation Timelines","history":"","full_text":"a The adopted evaluation form, evaluation procedures, and evaluation timelines shall be made available to the employees.\r\rb Employees new to the district may be evaluated initially at any time during the period from September through December 10, with final evaluation conferences held within twenty-one (21) calendar days after the first observation but no later than December 15th. The second evaluation for employees new to the district shall be conducted at any time during the period from January through the last day of March, with final evaluation conferences held no later than the first Thursday in April.\r\rc Employees, not new to the district, who are working under one year limited contracts or serving in the second year of a two year limited contract may be evaluated at any time during the period from September through December 10, with the final evaluation conferences held within twenty one (21) calendar days after the first observation but no later than December 15th. Any necessary subsequent evaluations shall be conducted at any time during the period from January through the last day of March, with the final evaluation conference held no later than the first Thursday in April.\r\rd Employees working under a continuing contract or in the initial year of a two year limited contract may be evaluated at any time during the period from September through the first Thursday in May, with the final evaluation conferences held no later than May 25 of each school year.\r\re Observation and\/or evaluation conferences shall not be scheduled the first week of school or on the day before or after a school holiday or vacation.\r\r","ancestry":{"1":{"id":"9","name":"Evaluation","identifier":"VIII","label":"Article","url":"http:\/\/localhost\/VIII\/"}},"structure_contents":{"0":{"id":"43","structure_id":"9","section_number":"8.01","catch_line":"Objectives Philosophy of Evaluation","url":"http:\/\/localhost\/8.01\/","api_url":"http:\/\/localhost\/api\/law\/8.01\/"},"1":{"id":"44","structure_id":"9","section_number":"8.02","catch_line":"Purpose of Evaluation","url":"http:\/\/localhost\/8.02\/","api_url":"http:\/\/localhost\/api\/law\/8.02\/"},"2":{"id":"45","structure_id":"9","section_number":"8.03","catch_line":"Frequency of Evaluation","url":"http:\/\/localhost\/8.03\/","api_url":"http:\/\/localhost\/api\/law\/8.03\/"},"3":{"id":"46","structure_id":"9","section_number":"8.04","catch_line":"Evaluation Procedures","url":"http:\/\/localhost\/8.04\/","api_url":"http:\/\/localhost\/api\/law\/8.04\/"},"4":{"id":"47","structure_id":"9","section_number":"8.05","catch_line":"Evaluation Deficiencies","url":"http:\/\/localhost\/8.05\/","api_url":"http:\/\/localhost\/api\/law\/8.05\/"},"5":{"id":"48","structure_id":"9","section_number":"8.06","catch_line":"Evaluation Timelines","url":"http:\/\/localhost\/8.06\/","api_url":"http:\/\/localhost\/api\/law\/8.06\/"},"6":{"id":"49","structure_id":"9","section_number":"8.07","catch_line":"Evaluation Criteria and Instrument","url":"http:\/\/localhost\/8.07\/","api_url":"http:\/\/localhost\/api\/law\/8.07\/"},"7":{"id":"50","structure_id":"9","section_number":"8.08","catch_line":"Evaluation and Grievance Procedure","url":"http:\/\/localhost\/8.08\/","api_url":"http:\/\/localhost\/api\/law\/8.08\/"},"8":{"id":"51","structure_id":"9","section_number":"8.09","catch_line":"Contract Evaluation Procedures and State Statutes","url":"http:\/\/localhost\/8.09\/","api_url":"http:\/\/localhost\/api\/law\/8.09\/"}},"metadata":{"history":null},"references":false,"url":"http:\/\/localhost\/8.06\/","dublin_core":{"Title":"Evaluation Timelines","Type":"Text","Format":"text\/html","Identifier":"\u00a7 8.06","Relation":"Contract"},"html":"\r\n\t\t\t\t\t<section id=\"a\"><p>a. <span class=\"dictionary\"><\/span>The<span class=\"dictionary\"><\/span> <span class=\"dictionary\"><\/span>adopted<span class=\"dictionary\"><\/span> <span class=\"dictionary\"><\/span>evaluation<span class=\"dictionary\"><\/span> <span class=\"dictionary\"><\/span>form<span class=\"dictionary\"><\/span>, <span class=\"dictionary\"><\/span>evaluation<span class=\"dictionary\"><\/span> <span class=\"dictionary\"><\/span>procedures<span class=\"dictionary\"><\/span>, <span class=\"dictionary\"><\/span>and<span class=\"dictionary\"><\/span> <span class=\"dictionary\"><\/span>evaluation<span class=\"dictionary\"><\/span> <span class=\"dictionary\"><\/span>timelines<span class=\"dictionary\"><\/span> <span class=\"dictionary\"><\/span>shall<span class=\"dictionary\"><\/span> <span class=\"dictionary\"><\/span>be<span class=\"dictionary\"><\/span> <span class=\"dictionary\"><\/span>made<span class=\"dictionary\"><\/span> <span class=\"dictionary\"><\/span>available<span class=\"dictionary\"><\/span> <span class=\"dictionary\"><\/span>to<span class=\"dictionary\"><\/span> <span class=\"dictionary\"><\/span>the<span class=\"dictionary\"><\/span> <span class=\"dictionary\"><\/span>employees<span class=\"dictionary\"><\/span>. <a id=\"paragraph-169\" class=\"section-permalink\" href=\"\/\/localhost\/admin\/parser.php#a\">\u00b6<\/a><\/p><\/section>\r\n\t\t\t\t\t<section id=\"b\"><p>b. <span class=\"dictionary\"><\/span>Employees<span class=\"dictionary\"><\/span> <span class=\"dictionary\"><\/span>new<span class=\"dictionary\"><\/span> <span class=\"dictionary\"><\/span>to<span class=\"dictionary\"><\/span> <span class=\"dictionary\"><\/span>the<span class=\"dictionary\"><\/span> <span class=\"dictionary\"><\/span>district<span class=\"dictionary\"><\/span> <span class=\"dictionary\"><\/span>may<span class=\"dictionary\"><\/span> <span class=\"dictionary\"><\/span>be<span class=\"dictionary\"><\/span> <span class=\"dictionary\"><\/span>evaluated<span class=\"dictionary\"><\/span> <span class=\"dictionary\"><\/span>initially<span class=\"dictionary\"><\/span> <span class=\"dictionary\"><\/span>at<span class=\"dictionary\"><\/span> <span class=\"dictionary\"><\/span>any<span class=\"dictionary\"><\/span> <span class=\"dictionary\"><\/span>time<span class=\"dictionary\"><\/span> <span class=\"dictionary\"><\/span>during<span class=\"dictionary\"><\/span> <span class=\"dictionary\"><\/span>the<span class=\"dictionary\"><\/span> <span class=\"dictionary\"><\/span>period<span class=\"dictionary\"><\/span> <span class=\"dictionary\"><\/span>from<span class=\"dictionary\"><\/span> <span class=\"dictionary\"><\/span>September<span class=\"dictionary\"><\/span> <span class=\"dictionary\"><\/span>through<span class=\"dictionary\"><\/span> <span class=\"dictionary\"><\/span>December<span class=\"dictionary\"><\/span> <span class=\"dictionary\"><\/span>10<span class=\"dictionary\"><\/span>, <span class=\"dictionary\"><\/span>with<span class=\"dictionary\"><\/span> <span class=\"dictionary\"><\/span>final<span class=\"dictionary\"><\/span> <span class=\"dictionary\"><\/span>evaluation<span class=\"dictionary\"><\/span> <span class=\"dictionary\"><\/span>conferences<span class=\"dictionary\"><\/span> <span class=\"dictionary\"><\/span>held<span class=\"dictionary\"><\/span> <span class=\"dictionary\"><\/span>within<span class=\"dictionary\"><\/span> <span class=\"dictionary\"><\/span>twenty<span class=\"dictionary\"><\/span>-<span class=\"dictionary\"><\/span>one<span class=\"dictionary\"><\/span> (<span class=\"dictionary\"><\/span>21<span class=\"dictionary\"><\/span>) <span class=\"dictionary\"><\/span>calendar<span class=\"dictionary\"><\/span> <span class=\"dictionary\"><\/span>days<span class=\"dictionary\"><\/span> <span class=\"dictionary\"><\/span>after<span class=\"dictionary\"><\/span> <span class=\"dictionary\"><\/span>the<span class=\"dictionary\"><\/span> <span class=\"dictionary\"><\/span>first<span class=\"dictionary\"><\/span> <span class=\"dictionary\"><\/span>observation<span class=\"dictionary\"><\/span> <span class=\"dictionary\"><\/span>but<span class=\"dictionary\"><\/span> <span class=\"dictionary\"><\/span>no<span class=\"dictionary\"><\/span> <span class=\"dictionary\"><\/span>later<span class=\"dictionary\"><\/span> <span class=\"dictionary\"><\/span>than<span class=\"dictionary\"><\/span> <span class=\"dictionary\"><\/span>December<span class=\"dictionary\"><\/span> <span class=\"dictionary\"><\/span>15th<span class=\"dictionary\"><\/span>. <span class=\"dictionary\"><\/span>The<span class=\"dictionary\"><\/span> <span class=\"dictionary\"><\/span>second<span class=\"dictionary\"><\/span> <span class=\"dictionary\"><\/span>evaluation<span class=\"dictionary\"><\/span> <span class=\"dictionary\"><\/span>for<span class=\"dictionary\"><\/span> <span class=\"dictionary\"><\/span>employees<span class=\"dictionary\"><\/span> <span class=\"dictionary\"><\/span>new<span class=\"dictionary\"><\/span> <span class=\"dictionary\"><\/span>to<span class=\"dictionary\"><\/span> <span class=\"dictionary\"><\/span>the<span class=\"dictionary\"><\/span> <span class=\"dictionary\"><\/span>district<span class=\"dictionary\"><\/span> <span class=\"dictionary\"><\/span>shall<span class=\"dictionary\"><\/span> <span class=\"dictionary\"><\/span>be<span class=\"dictionary\"><\/span> <span class=\"dictionary\"><\/span>conducted<span class=\"dictionary\"><\/span> <span class=\"dictionary\"><\/span>at<span class=\"dictionary\"><\/span> <span class=\"dictionary\"><\/span>any<span class=\"dictionary\"><\/span> <span class=\"dictionary\"><\/span>time<span class=\"dictionary\"><\/span> <span class=\"dictionary\"><\/span>during<span class=\"dictionary\"><\/span> <span class=\"dictionary\"><\/span>the<span class=\"dictionary\"><\/span> <span class=\"dictionary\"><\/span>period<span class=\"dictionary\"><\/span> <span class=\"dictionary\"><\/span>from<span class=\"dictionary\"><\/span> <span class=\"dictionary\"><\/span>January<span class=\"dictionary\"><\/span> <span class=\"dictionary\"><\/span>through<span class=\"dictionary\"><\/span> <span class=\"dictionary\"><\/span>the<span class=\"dictionary\"><\/span> <span class=\"dictionary\"><\/span>last<span class=\"dictionary\"><\/span> <span class=\"dictionary\"><\/span>day<span class=\"dictionary\"><\/span> <span class=\"dictionary\"><\/span>of<span class=\"dictionary\"><\/span> <span class=\"dictionary\"><\/span>March<span class=\"dictionary\"><\/span>, <span class=\"dictionary\"><\/span>with<span class=\"dictionary\"><\/span> <span class=\"dictionary\"><\/span>final<span class=\"dictionary\"><\/span> <span class=\"dictionary\"><\/span>evaluation<span class=\"dictionary\"><\/span> <span class=\"dictionary\"><\/span>conferences<span class=\"dictionary\"><\/span> <span class=\"dictionary\"><\/span>held<span class=\"dictionary\"><\/span> <span class=\"dictionary\"><\/span>no<span class=\"dictionary\"><\/span> <span class=\"dictionary\"><\/span>later<span class=\"dictionary\"><\/span> <span class=\"dictionary\"><\/span>than<span class=\"dictionary\"><\/span> <span class=\"dictionary\"><\/span>the<span class=\"dictionary\"><\/span> <span class=\"dictionary\"><\/span>first<span class=\"dictionary\"><\/span> <span class=\"dictionary\"><\/span>Thursday<span class=\"dictionary\"><\/span> <span class=\"dictionary\"><\/span>in<span class=\"dictionary\"><\/span> <span class=\"dictionary\"><\/span>April<span class=\"dictionary\"><\/span>. <a id=\"paragraph-170\" class=\"section-permalink\" href=\"\/\/localhost\/admin\/parser.php#b\">\u00b6<\/a><\/p><\/section>\r\n\t\t\t\t\t<section id=\"c\"><p>c. <span class=\"dictionary\"><\/span>Employees<span class=\"dictionary\"><\/span>, <span class=\"dictionary\"><\/span>not<span class=\"dictionary\"><\/span> <span class=\"dictionary\"><\/span>new<span class=\"dictionary\"><\/span> <span class=\"dictionary\"><\/span>to<span class=\"dictionary\"><\/span> <span class=\"dictionary\"><\/span>the<span class=\"dictionary\"><\/span> <span class=\"dictionary\"><\/span>district<span class=\"dictionary\"><\/span>, <span class=\"dictionary\"><\/span>who<span class=\"dictionary\"><\/span> <span class=\"dictionary\"><\/span>are<span class=\"dictionary\"><\/span> <span class=\"dictionary\"><\/span>working<span class=\"dictionary\"><\/span> <span class=\"dictionary\"><\/span>under<span class=\"dictionary\"><\/span> <span class=\"dictionary\"><\/span>one<span class=\"dictionary\"><\/span> <span class=\"dictionary\"><\/span>year<span class=\"dictionary\"><\/span> <span class=\"dictionary\"><\/span>limited<span class=\"dictionary\"><\/span> <span class=\"dictionary\"><\/span>contracts<span class=\"dictionary\"><\/span> <span class=\"dictionary\"><\/span>or<span class=\"dictionary\"><\/span> <span class=\"dictionary\"><\/span>serving<span class=\"dictionary\"><\/span> <span class=\"dictionary\"><\/span>in<span class=\"dictionary\"><\/span> <span class=\"dictionary\"><\/span>the<span class=\"dictionary\"><\/span> <span class=\"dictionary\"><\/span>second<span class=\"dictionary\"><\/span> <span class=\"dictionary\"><\/span>year<span class=\"dictionary\"><\/span> <span class=\"dictionary\"><\/span>of<span class=\"dictionary\"><\/span> <span class=\"dictionary\"><\/span>a<span class=\"dictionary\"><\/span> <span class=\"dictionary\"><\/span>two<span class=\"dictionary\"><\/span> <span class=\"dictionary\"><\/span>year<span class=\"dictionary\"><\/span> <span class=\"dictionary\"><\/span>limited<span class=\"dictionary\"><\/span> <span class=\"dictionary\"><\/span>contract<span class=\"dictionary\"><\/span> <span class=\"dictionary\"><\/span>may<span class=\"dictionary\"><\/span> <span class=\"dictionary\"><\/span>be<span class=\"dictionary\"><\/span> <span class=\"dictionary\"><\/span>evaluated<span class=\"dictionary\"><\/span> <span class=\"dictionary\"><\/span>at<span class=\"dictionary\"><\/span> <span class=\"dictionary\"><\/span>any<span class=\"dictionary\"><\/span> <span class=\"dictionary\"><\/span>time<span class=\"dictionary\"><\/span> <span class=\"dictionary\"><\/span>during<span class=\"dictionary\"><\/span> <span class=\"dictionary\"><\/span>the<span class=\"dictionary\"><\/span> <span class=\"dictionary\"><\/span>period<span class=\"dictionary\"><\/span> <span class=\"dictionary\"><\/span>from<span class=\"dictionary\"><\/span> <span class=\"dictionary\"><\/span>September<span class=\"dictionary\"><\/span> <span class=\"dictionary\"><\/span>through<span class=\"dictionary\"><\/span> <span class=\"dictionary\"><\/span>December<span class=\"dictionary\"><\/span> <span class=\"dictionary\"><\/span>10<span class=\"dictionary\"><\/span>, <span class=\"dictionary\"><\/span>with<span class=\"dictionary\"><\/span> <span class=\"dictionary\"><\/span>the<span class=\"dictionary\"><\/span> <span class=\"dictionary\"><\/span>final<span class=\"dictionary\"><\/span> <span class=\"dictionary\"><\/span>evaluation<span class=\"dictionary\"><\/span> <span class=\"dictionary\"><\/span>conferences<span class=\"dictionary\"><\/span> <span class=\"dictionary\"><\/span>held<span class=\"dictionary\"><\/span> <span class=\"dictionary\"><\/span>within<span class=\"dictionary\"><\/span> <span class=\"dictionary\"><\/span>twenty<span class=\"dictionary\"><\/span> <span class=\"dictionary\"><\/span>one<span class=\"dictionary\"><\/span> (<span class=\"dictionary\"><\/span>21<span class=\"dictionary\"><\/span>) <span class=\"dictionary\"><\/span>calendar<span class=\"dictionary\"><\/span> <span class=\"dictionary\"><\/span>days<span class=\"dictionary\"><\/span> <span class=\"dictionary\"><\/span>after<span class=\"dictionary\"><\/span> <span class=\"dictionary\"><\/span>the<span class=\"dictionary\"><\/span> <span class=\"dictionary\"><\/span>first<span class=\"dictionary\"><\/span> <span class=\"dictionary\"><\/span>observation<span class=\"dictionary\"><\/span> <span class=\"dictionary\"><\/span>but<span class=\"dictionary\"><\/span> <span class=\"dictionary\"><\/span>no<span class=\"dictionary\"><\/span> <span class=\"dictionary\"><\/span>later<span class=\"dictionary\"><\/span> <span class=\"dictionary\"><\/span>than<span class=\"dictionary\"><\/span> <span class=\"dictionary\"><\/span>December<span class=\"dictionary\"><\/span> <span class=\"dictionary\"><\/span>15th<span class=\"dictionary\"><\/span>. <span class=\"dictionary\"><\/span>Any<span class=\"dictionary\"><\/span> <span class=\"dictionary\"><\/span>necessary<span class=\"dictionary\"><\/span> <span class=\"dictionary\"><\/span>subsequent<span class=\"dictionary\"><\/span> <span class=\"dictionary\"><\/span>evaluations<span class=\"dictionary\"><\/span> <span class=\"dictionary\"><\/span>shall<span class=\"dictionary\"><\/span> <span class=\"dictionary\"><\/span>be<span class=\"dictionary\"><\/span> <span class=\"dictionary\"><\/span>conducted<span class=\"dictionary\"><\/span> <span class=\"dictionary\"><\/span>at<span class=\"dictionary\"><\/span> <span class=\"dictionary\"><\/span>any<span class=\"dictionary\"><\/span> <span class=\"dictionary\"><\/span>time<span class=\"dictionary\"><\/span> <span class=\"dictionary\"><\/span>during<span class=\"dictionary\"><\/span> <span class=\"dictionary\"><\/span>the<span class=\"dictionary\"><\/span> <span class=\"dictionary\"><\/span>period<span class=\"dictionary\"><\/span> <span class=\"dictionary\"><\/span>from<span class=\"dictionary\"><\/span> <span class=\"dictionary\"><\/span>January<span class=\"dictionary\"><\/span> <span class=\"dictionary\"><\/span>through<span class=\"dictionary\"><\/span> <span class=\"dictionary\"><\/span>the<span class=\"dictionary\"><\/span> <span class=\"dictionary\"><\/span>last<span class=\"dictionary\"><\/span> <span class=\"dictionary\"><\/span>day<span class=\"dictionary\"><\/span> <span class=\"dictionary\"><\/span>of<span class=\"dictionary\"><\/span> <span class=\"dictionary\"><\/span>March<span class=\"dictionary\"><\/span>, <span class=\"dictionary\"><\/span>with<span class=\"dictionary\"><\/span> <span class=\"dictionary\"><\/span>the<span class=\"dictionary\"><\/span> <span class=\"dictionary\"><\/span>final<span class=\"dictionary\"><\/span> <span class=\"dictionary\"><\/span>evaluation<span class=\"dictionary\"><\/span> <span class=\"dictionary\"><\/span>conference<span class=\"dictionary\"><\/span> <span class=\"dictionary\"><\/span>held<span class=\"dictionary\"><\/span> <span class=\"dictionary\"><\/span>no<span class=\"dictionary\"><\/span> <span class=\"dictionary\"><\/span>later<span class=\"dictionary\"><\/span> <span class=\"dictionary\"><\/span>than<span class=\"dictionary\"><\/span> <span class=\"dictionary\"><\/span>the<span class=\"dictionary\"><\/span> <span class=\"dictionary\"><\/span>first<span class=\"dictionary\"><\/span> <span class=\"dictionary\"><\/span>Thursday<span class=\"dictionary\"><\/span> <span class=\"dictionary\"><\/span>in<span class=\"dictionary\"><\/span> <span class=\"dictionary\"><\/span>April<span class=\"dictionary\"><\/span>. <a id=\"paragraph-171\" class=\"section-permalink\" href=\"\/\/localhost\/admin\/parser.php#c\">\u00b6<\/a><\/p><\/section>\r\n\t\t\t\t\t<section id=\"d\"><p>d. <span class=\"dictionary\"><\/span>Employees<span class=\"dictionary\"><\/span> <span class=\"dictionary\"><\/span>working<span class=\"dictionary\"><\/span> <span class=\"dictionary\"><\/span>under<span class=\"dictionary\"><\/span> <span class=\"dictionary\"><\/span>a<span class=\"dictionary\"><\/span> <span class=\"dictionary\"><\/span>continuing<span class=\"dictionary\"><\/span> <span class=\"dictionary\"><\/span>contract<span class=\"dictionary\"><\/span> <span class=\"dictionary\"><\/span>or<span class=\"dictionary\"><\/span> <span class=\"dictionary\"><\/span>in<span class=\"dictionary\"><\/span> <span class=\"dictionary\"><\/span>the<span class=\"dictionary\"><\/span> <span class=\"dictionary\"><\/span>initial<span class=\"dictionary\"><\/span> <span class=\"dictionary\"><\/span>year<span class=\"dictionary\"><\/span> <span class=\"dictionary\"><\/span>of<span class=\"dictionary\"><\/span> <span class=\"dictionary\"><\/span>a<span class=\"dictionary\"><\/span> <span class=\"dictionary\"><\/span>two<span class=\"dictionary\"><\/span> <span class=\"dictionary\"><\/span>year<span class=\"dictionary\"><\/span> <span class=\"dictionary\"><\/span>limited<span class=\"dictionary\"><\/span> <span class=\"dictionary\"><\/span>contract<span class=\"dictionary\"><\/span> <span class=\"dictionary\"><\/span>may<span class=\"dictionary\"><\/span> <span class=\"dictionary\"><\/span>be<span class=\"dictionary\"><\/span> <span class=\"dictionary\"><\/span>evaluated<span class=\"dictionary\"><\/span> <span class=\"dictionary\"><\/span>at<span class=\"dictionary\"><\/span> <span class=\"dictionary\"><\/span>any<span class=\"dictionary\"><\/span> <span class=\"dictionary\"><\/span>time<span class=\"dictionary\"><\/span> <span class=\"dictionary\"><\/span>during<span class=\"dictionary\"><\/span> <span class=\"dictionary\"><\/span>the<span class=\"dictionary\"><\/span> <span class=\"dictionary\"><\/span>period<span class=\"dictionary\"><\/span> <span class=\"dictionary\"><\/span>from<span class=\"dictionary\"><\/span> <span class=\"dictionary\"><\/span>September<span class=\"dictionary\"><\/span> <span class=\"dictionary\"><\/span>through<span class=\"dictionary\"><\/span> <span class=\"dictionary\"><\/span>the<span class=\"dictionary\"><\/span> <span class=\"dictionary\"><\/span>first<span class=\"dictionary\"><\/span> <span class=\"dictionary\"><\/span>Thursday<span class=\"dictionary\"><\/span> <span class=\"dictionary\"><\/span>in<span class=\"dictionary\"><\/span> <span class=\"dictionary\"><\/span>May<span class=\"dictionary\"><\/span>, <span class=\"dictionary\"><\/span>with<span class=\"dictionary\"><\/span> <span class=\"dictionary\"><\/span>the<span class=\"dictionary\"><\/span> <span class=\"dictionary\"><\/span>final<span class=\"dictionary\"><\/span> <span class=\"dictionary\"><\/span>evaluation<span class=\"dictionary\"><\/span> <span class=\"dictionary\"><\/span>conferences<span class=\"dictionary\"><\/span> <span class=\"dictionary\"><\/span>held<span class=\"dictionary\"><\/span> <span class=\"dictionary\"><\/span>no<span class=\"dictionary\"><\/span> <span class=\"dictionary\"><\/span>later<span class=\"dictionary\"><\/span> <span class=\"dictionary\"><\/span>than<span class=\"dictionary\"><\/span> <span class=\"dictionary\"><\/span>May<span class=\"dictionary\"><\/span> <span class=\"dictionary\"><\/span>25<span class=\"dictionary\"><\/span> <span class=\"dictionary\"><\/span>of<span class=\"dictionary\"><\/span> <span class=\"dictionary\"><\/span>each<span class=\"dictionary\"><\/span> <span class=\"dictionary\"><\/span>school<span class=\"dictionary\"><\/span> <span class=\"dictionary\"><\/span>year<span class=\"dictionary\"><\/span>. <a id=\"paragraph-172\" class=\"section-permalink\" href=\"\/\/localhost\/admin\/parser.php#d\">\u00b6<\/a><\/p><\/section>\r\n\t\t\t\t\t<section id=\"e\"><p>e. <span class=\"dictionary\"><\/span>Observation<span class=\"dictionary\"><\/span> <span class=\"dictionary\"><\/span>and<span class=\"dictionary\"><\/span>\/<span class=\"dictionary\"><\/span>or<span class=\"dictionary\"><\/span> <span class=\"dictionary\"><\/span>evaluation<span class=\"dictionary\"><\/span> <span class=\"dictionary\"><\/span>conferences<span class=\"dictionary\"><\/span> <span class=\"dictionary\"><\/span>shall<span class=\"dictionary\"><\/span> <span class=\"dictionary\"><\/span>not<span class=\"dictionary\"><\/span> <span class=\"dictionary\"><\/span>be<span class=\"dictionary\"><\/span> <span class=\"dictionary\"><\/span>scheduled<span class=\"dictionary\"><\/span> <span class=\"dictionary\"><\/span>the<span class=\"dictionary\"><\/span> <span class=\"dictionary\"><\/span>first<span class=\"dictionary\"><\/span> <span class=\"dictionary\"><\/span>week<span class=\"dictionary\"><\/span> <span class=\"dictionary\"><\/span>of<span class=\"dictionary\"><\/span> <span class=\"dictionary\"><\/span>school<span class=\"dictionary\"><\/span> <span class=\"dictionary\"><\/span>or<span class=\"dictionary\"><\/span> <span class=\"dictionary\"><\/span>on<span class=\"dictionary\"><\/span> <span class=\"dictionary\"><\/span>the<span class=\"dictionary\"><\/span> <span class=\"dictionary\"><\/span>day<span class=\"dictionary\"><\/span> <span class=\"dictionary\"><\/span>before<span class=\"dictionary\"><\/span> <span class=\"dictionary\"><\/span>or<span class=\"dictionary\"><\/span> <span class=\"dictionary\"><\/span>after<span class=\"dictionary\"><\/span> <span class=\"dictionary\"><\/span>a<span class=\"dictionary\"><\/span> <span class=\"dictionary\"><\/span>school<span class=\"dictionary\"><\/span> <span class=\"dictionary\"><\/span>holiday<span class=\"dictionary\"><\/span> <span class=\"dictionary\"><\/span>or<span class=\"dictionary\"><\/span> <span class=\"dictionary\"><\/span>vacation<span class=\"dictionary\"><\/span>. <a id=\"paragraph-173\" class=\"section-permalink\" href=\"\/\/localhost\/admin\/parser.php#e\">\u00b6<\/a><\/p><\/section>","plain_text":"                                     CONTRACT\n\nEVALUATION TIMELINES (\u00a7 8.06)\n\na. The adopted evaluation form, evaluation procedures, and evaluation timelines\nshall be made available to the employees.\n\nb. Employees new to the district may be evaluated initially at any time during\nthe period from September through December 10, with final evaluation conferences\nheld within twenty-one (21) calendar days after the first observation but no\nlater than December 15th. The second evaluation for employees new to the\ndistrict shall be conducted at any time during the period from January through\nthe last day of March, with final evaluation conferences held no later than the\nfirst Thursday in April.\n\nc. Employees, not new to the district, who are working under one year limited\ncontracts or serving in the second year of a two year limited contract may be\nevaluated at any time during the period from September through December 10, with\nthe final evaluation conferences held within twenty one (21) calendar days after\nthe first observation but no later than December 15th. Any necessary subsequent\nevaluations shall be conducted at any time during the period from January\nthrough the last day of March, with the final evaluation conference held no\nlater than the first Thursday in April.\n\nd. Employees working under a continuing contract or in the initial year of a two\nyear limited contract may be evaluated at any time during the period from\nSeptember through the first Thursday in May, with the final evaluation\nconferences held no later than May 25 of each school year.\n\ne. Observation and\/or evaluation conferences shall not be scheduled the first\nweek of school or on the day before or after a school holiday or vacation.\n","next_section":{"id":"49","structure_id":"9","section_number":"8.07","catch_line":"Evaluation Criteria and Instrument","url":"http:\/\/localhost\/8.07\/","api_url":"http:\/\/localhost\/api\/law\/8.07\/"},"previous_section":{"id":"47","structure_id":"9","section_number":"8.05","catch_line":"Evaluation Deficiencies","url":"http:\/\/localhost\/8.05\/","api_url":"http:\/\/localhost\/api\/law\/8.05\/"},"text":{"0":{"id":"169","text":"The adopted evaluation form, evaluation procedures, and evaluation timelines shall be made available to the employees.","type":"section","prefixes":["a"],"prefix":"a","entire_prefix":"a","prefix_anchor":"a","level":1,"next_prefix":"b"},"1":{"id":"170","text":"Employees new to the district may be evaluated initially at any time during the period from September through December 10, with final evaluation conferences held within twenty-one (21) calendar days after the first observation but no later than December 15th. The second evaluation for employees new to the district shall be conducted at any time during the period from January through the last day of March, with final evaluation conferences held no later than the first Thursday in April.","type":"section","prefixes":["b"],"prefix":"b","entire_prefix":"b","prefix_anchor":"b","level":1,"prior_prefix":"a","next_prefix":"c"},"2":{"id":"171","text":"Employees, not new to the district, who are working under one year limited contracts or serving in the second year of a two year limited contract may be evaluated at any time during the period from September through December 10, with the final evaluation conferences held within twenty one (21) calendar days after the first observation but no later than December 15th. Any necessary subsequent evaluations shall be conducted at any time during the period from January through the last day of March, with the final evaluation conference held no later than the first Thursday in April.","type":"section","prefixes":["c"],"prefix":"c","entire_prefix":"c","prefix_anchor":"c","level":1,"prior_prefix":"b","next_prefix":"d"},"3":{"id":"172","text":"Employees working under a continuing contract or in the initial year of a two year limited contract may be evaluated at any time during the period from September through the first Thursday in May, with the final evaluation conferences held no later than May 25 of each school year.","type":"section","prefixes":["d"],"prefix":"d","entire_prefix":"d","prefix_anchor":"d","level":1,"prior_prefix":"c","next_prefix":"e"},"4":{"id":"173","text":"Observation and\/or evaluation conferences shall not be scheduled the first week of school or on the day before or after a school holiday or vacation.","type":"section","prefixes":["e"],"prefix":"e","entire_prefix":"e","prefix_anchor":"e","level":1,"prior_prefix":"d"}}}