{"section_number":"18.01","section_id":"113","structure_id":"19","catch_line":"Severance Pay","history":"","full_text":"a An employee who has been employed in the District for ten (10) years and who, upon leaving the employment of the District, retires and begins to receive benefits from the State Teachers Retirement System, State of Ohio, shall receive severance pay in an amount equal to twenty-five percent (25%) of the employee\u2019s accumulated but unused sick leave, including personal days converted to sick leave pursuant to other provisions of this Agreement in excess of the maximum sick leave accumulation, if appropriate to do so pursuant to such other provisions.\r\rb Solely for the purposes of this Article, an employee with ten (10) years of service who dies while in active service of the Springboro Community City School District is deemed to have retired the day prior to his\/her death.\r\rc Severance pay shall be paid in January on the second payroll following the year of retirement of an employee, as elected by the Board.\r\r","ancestry":{"1":{"id":"19","name":"Fringe Benefit Provisions","identifier":"XVIII","label":"Article","url":"http:\/\/localhost\/XVIII\/"}},"structure_contents":{"0":{"id":"113","structure_id":"19","section_number":"18.01","catch_line":"Severance Pay","url":"http:\/\/localhost\/18.01\/","api_url":"http:\/\/localhost\/api\/law\/18.01\/"},"1":{"id":"114","structure_id":"19","section_number":"18.02","catch_line":"Insurance Program","url":"http:\/\/localhost\/18.02\/","api_url":"http:\/\/localhost\/api\/law\/18.02\/"},"2":{"id":"115","structure_id":"19","section_number":"18.03","catch_line":"STRS Pick-Up","url":"http:\/\/localhost\/18.03\/","api_url":"http:\/\/localhost\/api\/law\/18.03\/"},"3":{"id":"116","structure_id":"19","section_number":"18.04","catch_line":"IRS Section 125 Plan","url":"http:\/\/localhost\/18.04\/","api_url":"http:\/\/localhost\/api\/law\/18.04\/"},"4":{"id":"117","structure_id":"19","section_number":"18.05","catch_line":"Mileage Reimbursement","url":"http:\/\/localhost\/18.05\/","api_url":"http:\/\/localhost\/api\/law\/18.05\/"},"5":{"id":"118","structure_id":"19","section_number":"18.06","catch_line":"Tuition Reimbursement\/Professional Development","url":"http:\/\/localhost\/18.06\/","api_url":"http:\/\/localhost\/api\/law\/18.06\/"}},"metadata":{"history":null},"references":false,"url":"http:\/\/localhost\/18.01\/","dublin_core":{"Title":"Severance Pay","Type":"Text","Format":"text\/html","Identifier":"\u00a7 18.01","Relation":"Contract"},"html":"\r\n\t\t\t\t\t<section id=\"a\"><p>a. <span class=\"dictionary\"><\/span>An<span class=\"dictionary\"><\/span> <span class=\"dictionary\"><\/span>employee<span class=\"dictionary\"><\/span> <span class=\"dictionary\"><\/span>who<span class=\"dictionary\"><\/span> <span class=\"dictionary\"><\/span>has<span class=\"dictionary\"><\/span> <span class=\"dictionary\"><\/span>been<span class=\"dictionary\"><\/span> <span class=\"dictionary\"><\/span>employed<span class=\"dictionary\"><\/span> <span class=\"dictionary\"><\/span>in<span class=\"dictionary\"><\/span> <span class=\"dictionary\"><\/span>the<span class=\"dictionary\"><\/span> <span class=\"dictionary\"><\/span>District<span class=\"dictionary\"><\/span> <span class=\"dictionary\"><\/span>for<span class=\"dictionary\"><\/span> <span class=\"dictionary\"><\/span>ten<span class=\"dictionary\"><\/span> (<span class=\"dictionary\"><\/span>10<span class=\"dictionary\"><\/span>) <span class=\"dictionary\"><\/span>years<span class=\"dictionary\"><\/span> <span class=\"dictionary\"><\/span>and<span class=\"dictionary\"><\/span> <span class=\"dictionary\"><\/span>who<span class=\"dictionary\"><\/span>, <span class=\"dictionary\"><\/span>upon<span class=\"dictionary\"><\/span> <span class=\"dictionary\"><\/span>leaving<span class=\"dictionary\"><\/span> <span class=\"dictionary\"><\/span>the<span class=\"dictionary\"><\/span> <span class=\"dictionary\"><\/span>employment<span class=\"dictionary\"><\/span> <span class=\"dictionary\"><\/span>of<span class=\"dictionary\"><\/span> <span class=\"dictionary\"><\/span>the<span class=\"dictionary\"><\/span> <span class=\"dictionary\"><\/span>District<span class=\"dictionary\"><\/span>, <span class=\"dictionary\"><\/span>retires<span class=\"dictionary\"><\/span> <span class=\"dictionary\"><\/span>and<span class=\"dictionary\"><\/span> <span class=\"dictionary\"><\/span>begins<span class=\"dictionary\"><\/span> <span class=\"dictionary\"><\/span>to<span class=\"dictionary\"><\/span> <span class=\"dictionary\"><\/span>receive<span class=\"dictionary\"><\/span> <span class=\"dictionary\"><\/span>benefits<span class=\"dictionary\"><\/span> <span class=\"dictionary\"><\/span>from<span class=\"dictionary\"><\/span> <span class=\"dictionary\"><\/span>the<span class=\"dictionary\"><\/span> <span class=\"dictionary\"><\/span>State<span class=\"dictionary\"><\/span> <span class=\"dictionary\"><\/span>Teachers<span class=\"dictionary\"><\/span> <span class=\"dictionary\"><\/span>Retirement<span class=\"dictionary\"><\/span> <span class=\"dictionary\"><\/span>System<span class=\"dictionary\"><\/span>, <span class=\"dictionary\"><\/span>State<span class=\"dictionary\"><\/span> <span class=\"dictionary\"><\/span>of<span class=\"dictionary\"><\/span> <span class=\"dictionary\"><\/span>Ohio<span class=\"dictionary\"><\/span>, <span class=\"dictionary\"><\/span>shall<span class=\"dictionary\"><\/span> <span class=\"dictionary\"><\/span>receive<span class=\"dictionary\"><\/span> <span class=\"dictionary\"><\/span>severance<span class=\"dictionary\"><\/span> <span class=\"dictionary\"><\/span>pay<span class=\"dictionary\"><\/span> <span class=\"dictionary\"><\/span>in<span class=\"dictionary\"><\/span> <span class=\"dictionary\"><\/span>an<span class=\"dictionary\"><\/span> <span class=\"dictionary\"><\/span>amount<span class=\"dictionary\"><\/span> <span class=\"dictionary\"><\/span>equal<span class=\"dictionary\"><\/span> <span class=\"dictionary\"><\/span>to<span class=\"dictionary\"><\/span> <span class=\"dictionary\"><\/span>twenty<span class=\"dictionary\"><\/span>-<span class=\"dictionary\"><\/span>five<span class=\"dictionary\"><\/span> <span class=\"dictionary\"><\/span>percent<span class=\"dictionary\"><\/span> (<span class=\"dictionary\"><\/span>25<span class=\"dictionary\"><\/span>%) <span class=\"dictionary\"><\/span>of<span class=\"dictionary\"><\/span> <span class=\"dictionary\"><\/span>the<span class=\"dictionary\"><\/span> <span class=\"dictionary\"><\/span>employee<span class=\"dictionary\"><\/span>\u2019<span class=\"dictionary\">s<\/span><span class=\"dictionary\"><\/span> <span class=\"dictionary\"><\/span>accumulated<span class=\"dictionary\"><\/span> <span class=\"dictionary\"><\/span>but<span class=\"dictionary\"><\/span> <span class=\"dictionary\"><\/span>unused<span class=\"dictionary\"><\/span> <span class=\"dictionary\"><\/span>sick<span class=\"dictionary\"><\/span> <span class=\"dictionary\"><\/span>leave<span class=\"dictionary\"><\/span>, <span class=\"dictionary\"><\/span>including<span class=\"dictionary\"><\/span> <span class=\"dictionary\"><\/span>personal<span class=\"dictionary\"><\/span> <span class=\"dictionary\"><\/span>days<span class=\"dictionary\"><\/span> <span class=\"dictionary\"><\/span>converted<span class=\"dictionary\"><\/span> <span class=\"dictionary\"><\/span>to<span class=\"dictionary\"><\/span> <span class=\"dictionary\"><\/span>sick<span class=\"dictionary\"><\/span> <span class=\"dictionary\"><\/span>leave<span class=\"dictionary\"><\/span> <span class=\"dictionary\"><\/span>pursuant<span class=\"dictionary\"><\/span> <span class=\"dictionary\"><\/span>to<span class=\"dictionary\"><\/span> <span class=\"dictionary\"><\/span>other<span class=\"dictionary\"><\/span> <span class=\"dictionary\"><\/span>provisions<span class=\"dictionary\"><\/span> <span class=\"dictionary\"><\/span>of<span class=\"dictionary\"><\/span> <span class=\"dictionary\"><\/span>this<span class=\"dictionary\"><\/span> <span class=\"dictionary\"><\/span>Agreement<span class=\"dictionary\"><\/span> <span class=\"dictionary\"><\/span>in<span class=\"dictionary\"><\/span> <span class=\"dictionary\"><\/span>excess<span class=\"dictionary\"><\/span> <span class=\"dictionary\"><\/span>of<span class=\"dictionary\"><\/span> <span class=\"dictionary\"><\/span>the<span class=\"dictionary\"><\/span> <span class=\"dictionary\"><\/span>maximum<span class=\"dictionary\"><\/span> <span class=\"dictionary\"><\/span>sick<span class=\"dictionary\"><\/span> <span class=\"dictionary\"><\/span>leave<span class=\"dictionary\"><\/span> <span class=\"dictionary\"><\/span>accumulation<span class=\"dictionary\"><\/span>, <span class=\"dictionary\"><\/span>if<span class=\"dictionary\"><\/span> <span class=\"dictionary\"><\/span>appropriate<span class=\"dictionary\"><\/span> <span class=\"dictionary\"><\/span>to<span class=\"dictionary\"><\/span> <span class=\"dictionary\"><\/span>do<span class=\"dictionary\"><\/span> <span class=\"dictionary\"><\/span>so<span class=\"dictionary\"><\/span> <span class=\"dictionary\"><\/span>pursuant<span class=\"dictionary\"><\/span> <span class=\"dictionary\"><\/span>to<span class=\"dictionary\"><\/span> <span class=\"dictionary\"><\/span>such<span class=\"dictionary\"><\/span> <span class=\"dictionary\"><\/span>other<span class=\"dictionary\"><\/span> <span class=\"dictionary\"><\/span>provisions<span class=\"dictionary\"><\/span>. <a id=\"paragraph-519\" class=\"section-permalink\" href=\"\/\/localhost\/admin\/parser.php#a\">\u00b6<\/a><\/p><\/section>\r\n\t\t\t\t\t<section id=\"b\"><p>b. <span class=\"dictionary\"><\/span>Solely<span class=\"dictionary\"><\/span> <span class=\"dictionary\"><\/span>for<span class=\"dictionary\"><\/span> <span class=\"dictionary\"><\/span>the<span class=\"dictionary\"><\/span> <span class=\"dictionary\"><\/span>purposes<span class=\"dictionary\"><\/span> <span class=\"dictionary\"><\/span>of<span class=\"dictionary\"><\/span> <span class=\"dictionary\"><\/span>this<span class=\"dictionary\"><\/span> <span class=\"dictionary\"><\/span>Article<span class=\"dictionary\"><\/span>, <span class=\"dictionary\"><\/span>an<span class=\"dictionary\"><\/span> <span class=\"dictionary\"><\/span>employee<span class=\"dictionary\"><\/span> <span class=\"dictionary\"><\/span>with<span class=\"dictionary\"><\/span> <span class=\"dictionary\"><\/span>ten<span class=\"dictionary\"><\/span> (<span class=\"dictionary\"><\/span>10<span class=\"dictionary\"><\/span>) <span class=\"dictionary\"><\/span>years<span class=\"dictionary\"><\/span> <span class=\"dictionary\"><\/span>of<span class=\"dictionary\"><\/span> <span class=\"dictionary\"><\/span>service<span class=\"dictionary\"><\/span> <span class=\"dictionary\"><\/span>who<span class=\"dictionary\"><\/span> <span class=\"dictionary\"><\/span>dies<span class=\"dictionary\"><\/span> <span class=\"dictionary\"><\/span>while<span class=\"dictionary\"><\/span> <span class=\"dictionary\"><\/span>in<span class=\"dictionary\"><\/span> <span class=\"dictionary\"><\/span>active<span class=\"dictionary\"><\/span> <span class=\"dictionary\"><\/span>service<span class=\"dictionary\"><\/span> <span class=\"dictionary\"><\/span>of<span class=\"dictionary\"><\/span> <span class=\"dictionary\"><\/span>the<span class=\"dictionary\"><\/span> <span class=\"dictionary\"><\/span>Springboro<span class=\"dictionary\"><\/span> <span class=\"dictionary\"><\/span>Community<span class=\"dictionary\"><\/span> <span class=\"dictionary\"><\/span>City<span class=\"dictionary\"><\/span> <span class=\"dictionary\"><\/span>School<span class=\"dictionary\"><\/span> <span class=\"dictionary\"><\/span>District<span class=\"dictionary\"><\/span> <span class=\"dictionary\"><\/span>is<span class=\"dictionary\"><\/span> <span class=\"dictionary\"><\/span>deemed<span class=\"dictionary\"><\/span> <span class=\"dictionary\"><\/span>to<span class=\"dictionary\"><\/span> <span class=\"dictionary\"><\/span>have<span class=\"dictionary\"><\/span> <span class=\"dictionary\"><\/span>retired<span class=\"dictionary\"><\/span> <span class=\"dictionary\"><\/span>the<span class=\"dictionary\"><\/span> <span class=\"dictionary\"><\/span>day<span class=\"dictionary\"><\/span> <span class=\"dictionary\"><\/span>prior<span class=\"dictionary\"><\/span> <span class=\"dictionary\"><\/span>to<span class=\"dictionary\"><\/span> <span class=\"dictionary\"><\/span>his<span class=\"dictionary\"><\/span>\/<span class=\"dictionary\"><\/span>her<span class=\"dictionary\"><\/span> <span class=\"dictionary\"><\/span>death<span class=\"dictionary\"><\/span>. <a id=\"paragraph-520\" class=\"section-permalink\" href=\"\/\/localhost\/admin\/parser.php#b\">\u00b6<\/a><\/p><\/section>\r\n\t\t\t\t\t<section id=\"c\"><p>c. <span class=\"dictionary\"><\/span>Severance<span class=\"dictionary\"><\/span> <span class=\"dictionary\"><\/span>pay<span class=\"dictionary\"><\/span> <span class=\"dictionary\"><\/span>shall<span class=\"dictionary\"><\/span> <span class=\"dictionary\"><\/span>be<span class=\"dictionary\"><\/span> <span class=\"dictionary\"><\/span>paid<span class=\"dictionary\"><\/span> <span class=\"dictionary\"><\/span>in<span class=\"dictionary\"><\/span> <span class=\"dictionary\"><\/span>January<span class=\"dictionary\"><\/span> <span class=\"dictionary\"><\/span>on<span class=\"dictionary\"><\/span> <span class=\"dictionary\"><\/span>the<span class=\"dictionary\"><\/span> <span class=\"dictionary\"><\/span>second<span class=\"dictionary\"><\/span> <span class=\"dictionary\"><\/span>payroll<span class=\"dictionary\"><\/span> <span class=\"dictionary\"><\/span>following<span class=\"dictionary\"><\/span> <span class=\"dictionary\"><\/span>the<span class=\"dictionary\"><\/span> <span class=\"dictionary\"><\/span>year<span class=\"dictionary\"><\/span> <span class=\"dictionary\"><\/span>of<span class=\"dictionary\"><\/span> <span class=\"dictionary\"><\/span>retirement<span class=\"dictionary\"><\/span> <span class=\"dictionary\"><\/span>of<span class=\"dictionary\"><\/span> <span class=\"dictionary\"><\/span>an<span class=\"dictionary\"><\/span> <span class=\"dictionary\"><\/span>employee<span class=\"dictionary\"><\/span>, <span class=\"dictionary\"><\/span>as<span class=\"dictionary\"><\/span> <span class=\"dictionary\"><\/span>elected<span class=\"dictionary\"><\/span> <span class=\"dictionary\"><\/span>by<span class=\"dictionary\"><\/span> <span class=\"dictionary\"><\/span>the<span class=\"dictionary\"><\/span> <span class=\"dictionary\"><\/span>Board<span class=\"dictionary\"><\/span>. <a id=\"paragraph-521\" class=\"section-permalink\" href=\"\/\/localhost\/admin\/parser.php#c\">\u00b6<\/a><\/p><\/section>","plain_text":"                                     CONTRACT\n\nSEVERANCE PAY (\u00a7 18.01)\n\na. An employee who has been employed in the District for ten (10) years and who,\nupon leaving the employment of the District, retires and begins to receive\nbenefits from the State Teachers Retirement System, State of Ohio, shall receive\nseverance pay in an amount equal to twenty-five percent (25%) of the\nemployee\u2019s accumulated but unused sick leave, including personal days\nconverted to sick leave pursuant to other provisions of this Agreement in excess\nof the maximum sick leave accumulation, if appropriate to do so pursuant to such\nother provisions.\n\nb. Solely for the purposes of this Article, an employee with ten (10) years of\nservice who dies while in active service of the Springboro Community City School\nDistrict is deemed to have retired the day prior to his\/her death.\n\nc. Severance pay shall be paid in January on the second payroll following the\nyear of retirement of an employee, as elected by the Board.\n","next_section":{"id":"114","structure_id":"19","section_number":"18.02","catch_line":"Insurance Program","url":"http:\/\/localhost\/18.02\/","api_url":"http:\/\/localhost\/api\/law\/18.02\/"},"previous_section":{"id":"111","structure_id":"18","section_number":"17.06","catch_line":"Saturday School\/Administrative Detention","url":"http:\/\/localhost\/17.06\/","api_url":"http:\/\/localhost\/api\/law\/17.06\/"},"text":{"0":{"id":"519","text":"An employee who has been employed in the District for ten (10) years and who, upon leaving the employment of the District, retires and begins to receive benefits from the State Teachers Retirement System, State of Ohio, shall receive severance pay in an amount equal to twenty-five percent (25%) of the employee\u2019s accumulated but unused sick leave, including personal days converted to sick leave pursuant to other provisions of this Agreement in excess of the maximum sick leave accumulation, if appropriate to do so pursuant to such other provisions.","type":"section","prefixes":["a"],"prefix":"a","entire_prefix":"a","prefix_anchor":"a","level":1,"next_prefix":"b"},"1":{"id":"520","text":"Solely for the purposes of this Article, an employee with ten (10) years of service who dies while in active service of the Springboro Community City School District is deemed to have retired the day prior to his\/her death.","type":"section","prefixes":["b"],"prefix":"b","entire_prefix":"b","prefix_anchor":"b","level":1,"prior_prefix":"a","next_prefix":"c"},"2":{"id":"521","text":"Severance pay shall be paid in January on the second payroll following the year of retirement of an employee, as elected by the Board.","type":"section","prefixes":["c"],"prefix":"c","entire_prefix":"c","prefix_anchor":"c","level":1,"prior_prefix":"b"}}}